matchbox2/__init__.py
matchbox2/matchbox2.py
matchbox2/matchbox2_combiner.py
matchbox2/command/__init__.py
matchbox2/command/mb2_combiner_commands.py
matchbox2/command/mb2_laser_commands.py
matchbox2/models/__init__.py
matchbox2/models/laser_info.py
matchbox2/models/laser_on_port.py
matchbox2/models/laser_readings.py
matchbox2/models/laser_settings.py
matchbox2/parser/__init__.py
matchbox2/parser/combiner_command_parser.py
matchbox2/parser/laser_command_parser.py
matchbox2py-0.1.6.dist-info/METADATA
matchbox2py-0.1.6.dist-info/WHEEL
matchbox2py-0.1.6.dist-info/top_level.txt
matchbox2py-0.1.6.dist-info/RECORD
