Metadata-Version: 2.4
Name: matchbox2py
Version: 0.1.6
Summary: Official Python library for controlling Integrated Optics MatchBox2 laser modules via USB serial interface.
Author: Integrated Optics, UAB
License-Expression: MIT
Project-URL: Homepage, https://integratedoptics.com/
Project-URL: Repository, https://github.com/Integrated-optics/matchbox2py
Requires-Python: >=3.8
Requires-Dist: pyserial>=3.5
